README.rst
setup.py
cat/__init__.py
random_cat.egg-info/PKG-INFO
random_cat.egg-info/SOURCES.txt
random_cat.egg-info/dependency_links.txt
random_cat.egg-info/entry_points.txt
random_cat.egg-info/top_level.txt